mpeg_convert/.DS_Store
mpeg_convert/__main__.py
mpeg_convert/arguments.py
mpeg_convert/exceptions.py
mpeg_convert/module.py
mpeg_convert/term.py
mpeg_convert/utils.py
mpeg_convert/assets/default.yml
mpeg_convert/assets/help.txt
mpeg_convert-0.2.1.dist-info/LICENSE
mpeg_convert-0.2.1.dist-info/METADATA
mpeg_convert-0.2.1.dist-info/WHEEL
mpeg_convert-0.2.1.dist-info/entry_points.txt
mpeg_convert-0.2.1.dist-info/top_level.txt
mpeg_convert-0.2.1.dist-info/RECORD
