Metadata-Version: 2.1
Name: mpeg-convert
Version: 0.2.1
Summary: A python wrapper that enhances the user experience and productivity when using ffmpeg
Author: Zichen
License: MIT
Project-URL: Homepage, https://github.com/SomedudeX/mpeg-convert
Project-URL: Issues, https://github.com/SomedudeX/mpeg-convert/issues
Keywords: transcode,ffmpeg,convert,media,mp4,mp3
Classifier: Development Status :: 5 - Production/Stable
Classifier: Intended Audience :: End Users/Desktop
Classifier: License :: OSI Approved :: MIT License
Classifier: Programming Language :: Python :: 3 :: Only
Classifier: Programming Language :: Python
Classifier: Topic :: Multimedia
Classifier: Topic :: Utilities
Classifier: Environment :: Console
Requires-Python: >=3.7
License-File: LICENSE
Requires-Dist: rich >=13.7.0
Requires-Dist: pyyaml >=6.0.1
Requires-Dist: python-ffmpeg >=2.0.10
